catzzz
