Metadata-Version: 1.1
Name: catzzz
Version: 0.1.6
Summary: A package for getting more cats into your code.
Home-page: http://github.com/logston/catzzz
Author: Paul Logston
Author-email: code@logston.me
License: Copyright (c) 2014, Paul Logston
